{
    "Atr1": [
        4,
        1,
        0
    ],
    "Atr2": [
        3,
        1,
        2
    ],
    "Atr3": [
        3,
        1,
        2
    ],
    "Atr4": [
        3,
        1,
        1
    ],
    "Atr5": [
        4,
        1,
        0
    ],
    "Atr6": [
        1,
        2,
        0
    ],
    "Atr7": [
        0,
        0,
        0
    ],
    "Atr8": [
        3,
        2,
        0
    ],
    "Atr9": [
        3,
        2,
        0
    ],
    "Atr10": [
        3,
        2,
        2
    ],
    "Atr11": [
        4,
        3,
        1
    ],
    "Atr12": [
        3,
        0,
        1
    ],
    "Atr13": [
        4,
        0,
        1
    ],
    "Atr14": [
        3,
        2,
        0
    ],
    "Atr15": [
        3,
        1,
        0
    ],
    "Atr16": [
        3,
        0,
        0
    ],
    "Atr17": [
        4,
        1,
        0
    ],
    "Atr18": [
        3,
        2,
        0
    ],
    "Atr19": [
        4,
        1,
        0
    ],
    "Atr20": [
        3,
        0,
        0
    ],
    "Atr21": [
        3,
        0,
        0
    ],
    "Atr22": [
        3,
        0,
        0
    ],
    "Atr23": [
        4,
        0,
        0
    ],
    "Atr24": [
        3,
        1,
        0
    ],
    "Atr25": [
        4,
        1,
        1
    ],
    "Atr26": [
        3,
        1,
        0
    ],
    "Atr27": [
        3,
        1,
        0
    ],
    "Atr28": [
        3,
        1,
        0
    ],
    "Atr29": [
        4,
        1,
        0
    ],
    "Atr30": [
        3,
        1,
        0
    ],
    "Atr31": [
        4,
        1,
        1
    ],
    "Atr32": [
        4,
        1,
        3
    ],
    "Atr33": [
        4,
        0,
        0
    ],
    "Atr34": [
        4,
        1,
        0
    ],
    "Atr35": [
        4,
        0,
        0
    ],
    "Atr36": [
        4,
        0,
        0
    ],
    "Atr37": [
        4,
        1,
        2
    ],
    "Atr38": [
        4,
        1,
        1
    ],
    "Atr39": [
        4,
        2,
        1
    ],
    "Atr40": [
        4,
        2,
        0
    ],
    "Atr41": [
        4,
        1,
        2
    ],
    "Atr42": [
        4,
        2,
        0
    ],
    "Atr43": [
        4,
        3,
        0
    ],
    "Atr44": [
        4,
        2,
        0
    ],
    "Atr45": [
        4,
        2,
        0
    ],
    "Atr46": [
        4,
        2,
        0
    ],
    "Atr47": [
        4,
        0,
        0
    ],
    "Atr48": [
        4,
        2,
        3
    ],
    "Atr49": [
        4,
        2,
        1
    ],
    "Atr50": [
        4,
        2,
        1
    ],
    "Atr51": [
        4,
        2,
        1
    ],
    "Atr52": [
        4,
        4,
        0
    ],
    "Atr53": [
        4,
        3,
        3
    ],
    "Atr54": [
        4,
        3,
        0
    ]
}